dns_threat_detector/__init__.py
dns_threat_detector/check_install.py
dns_threat_detector/cli.py
dns_threat_detector/detector.py
dns_threat_detector/detector_v1_backup.py
dns_threat_detector/detector_v2.py
dns_threat_detector/models/lgbm_model_v2.pkl
dns_threat_detector/models/lgbm_typo_enhanced.pkl
dns_threat_detector/models/lstm_model.pth
dns_threat_detector/models/meta_learner.pkl
dns_threat_detector/models/tokenizer.pkl
dns_threat_detector/safelists/tier1_critical.txt
dns_threat_detector/safelists/tier2_high_trust.txt
dns_threat_detector/safelists/tier3_general.txt
dns_threat_detector-2.0.1.dist-info/licenses/LICENSE
tests/__init__.py
tests/test_detector.py
dns_threat_detector-2.0.1.dist-info/METADATA
dns_threat_detector-2.0.1.dist-info/WHEEL
dns_threat_detector-2.0.1.dist-info/entry_points.txt
dns_threat_detector-2.0.1.dist-info/top_level.txt
dns_threat_detector-2.0.1.dist-info/RECORD
