Metadata-Version: 2.4
Name: dns-threat-detector
Version: 2.0.1
Summary: Production-ready DNS threat detection using machine learning - Model-driven architecture
Home-page: https://github.com/SubratDash67/DNS-Security
Author: UMUDGA Project
Author-email: UMUDGA Project <contact@umudga.edu>
License: MIT
Project-URL: Homepage, https://github.com/SubratDash67/DNS-Security
Project-URL: Documentation, https://github.com/SubratDash67/DNS-Security/wiki
Project-URL: Repository, https://github.com/SubratDash67/DNS-Security
Project-URL: Bug Reports, https://github.com/SubratDash67/DNS-Security/issues
Keywords: dns,threat-detection,machine-learning,dga,typosquatting,security,cybersecurity,malware,phishing
Classifier: Development Status :: 5 - Production/Stable
Classifier: Intended Audience :: Developers
Classifier: Intended Audience :: Information Technology
Classifier: Topic :: Security
Classifier: Topic :: Internet :: Name Service (DNS)
Classifier: License :: OSI Approved :: MIT License
Classifier: Programming Language :: Python :: 3
Classifier: Programming Language :: Python :: 3.8
Classifier: Programming Language :: Python :: 3.9
Classifier: Programming Language :: Python :: 3.10
Classifier: Programming Language :: Python :: 3.11
Requires-Python: >=3.8
License-File: LICENSE
Requires-Dist: torch>=2.0.0
Requires-Dist: lightgbm>=4.0.0
Requires-Dist: scikit-learn>=1.3.0
Requires-Dist: pandas>=2.0.0
Requires-Dist: numpy>=1.24.0
Requires-Dist: tldextract>=3.0.0
Provides-Extra: dev
Requires-Dist: pytest>=7.0.0; extra == "dev"
Requires-Dist: pytest-cov>=4.0.0; extra == "dev"
Requires-Dist: black>=23.0.0; extra == "dev"
Requires-Dist: flake8>=6.0.0; extra == "dev"
Dynamic: author
Dynamic: home-page
Dynamic: license-file
Dynamic: requires-python
